folio_uuid/__init__.py
folio_uuid/folio_namespaces.py
folio_uuid/folio_uuid.py
folio_uuid-1.0.0.dist-info/WHEEL
folio_uuid-1.0.0.dist-info/METADATA
folio_uuid-1.0.0.dist-info/RECORD
