Metadata-Version: 2.4
Name: folio-uuid
Version: 1.0.0
Summary: A library for generating predictive uuids for FOLIO data migrations
Keywords: FOLIO,ILS,LSP,Library Systems,MARC21,Library data,UUID
Author: Theodor Tolstoy, Lisa Sjögren, Brooks Travis
Author-email: Theodor Tolstoy <github.teddes@tolstoy.se>, Brooks Travis <brooks.travis@gmail.com>
License-Expression: MIT
Requires-Python: >=3.10, <4.0
Project-URL: homepage, https://github.com/FOLIO-FSE/folio_uuid
Project-URL: repository, https://github.com/FOLIO-FSE/folio_uuid
